pointcloudlasso/__init__.py
pointcloudlasso/__init__.pyi
pointcloudlasso/_pointcloudlasso_ext.cpython-313-darwin.so
pointcloudlasso/py.typed
pointcloudlasso-0.1.0.dist-info/METADATA
pointcloudlasso-0.1.0.dist-info/WHEEL
pointcloudlasso-0.1.0.dist-info/RECORD
