Metadata-Version: 2.4
Name: pointcloudlasso
Version: 0.1.0
Classifier: Development Status :: 4 - Beta
Classifier: Intended Audience :: Developers
Classifier: Intended Audience :: Science/Research
Classifier: License :: OSI Approved :: MIT License
Classifier: Operating System :: OS Independent
Classifier: Programming Language :: Python :: 3
Classifier: Programming Language :: Python :: 3.10
Classifier: Programming Language :: Python :: 3.11
Classifier: Programming Language :: Python :: 3.12
Classifier: Programming Language :: Python :: 3.13
Classifier: Programming Language :: Rust
Classifier: Topic :: Scientific/Engineering :: GIS
Classifier: Topic :: Software Development :: Libraries :: Python Modules
Classifier: Typing :: Typed
Requires-Dist: numpy>=1.18.0
Requires-Dist: shapely>=2.0.1
Summary: Fast point-in-polygon tests for point clouds
Keywords: point-cloud,point-in-polygon,GIS,spatial,geometry,rust,numpy
Home-Page: https://github.com/dwastberg/pointcloudlasso
Author-email: Dag Wästberg <dwastberg@gmail.com>
License: MIT
Requires-Python: >=3.10
Project-URL: Documentation, https://github.com/dwastberg/pointcloudlasso/tree/main/py#readme
Project-URL: Homepage, https://github.com/dwastberg/pointcloudlasso
Project-URL: Issue Tracker, https://github.com/dwastberg/pointcloudlasso/issues
Project-URL: Repository, https://github.com/dwastberg/pointcloudlasso
